{
  "number": 169,
  "book": "Gushimisha",
  "title": "Mana, Nkuko Wafashaga Ba Sogukuruza",
  "slug": "mana-nkuko-wafashaga-ba-sogukuruza",
  "uuid": "ff94acb5-0670-11ea-9a58-deadbe058832",
  "category": "Ubugingo bushya",
  "url": "https://indirimbo.com/gushimisha/mana-nkuko-wafashaga-ba-sogukuruza/ff94acb5-0670-11ea-9a58-deadbe058832",
  "lyrics": [
    {
      "type": "verse",
      "number": 1,
      "lines": [
        "Mana, Nkuko  Wafashaga Ba Sogukuruza ,",
        "Niko Natweuzadufasha Mu Myak’irimbere."
      ]
    },
    {
      "type": "verse",
      "number": 2,
      "lines": [
        "Umuyaga W’ishuheri Urawuturinda.",
        "Uzatuber’ubuturo Budashir’iteka."
      ]
    },
    {
      "type": "verse",
      "number": 3,
      "lines": [
        "Kera Abakwiringiraga Bari Mu Mahoro.",
        "Tugufite, Ntitwifuza Undi Murengezi."
      ]
    },
    {
      "type": "verse",
      "number": 4,
      "lines": [
        "Imisoz’itararemwa,Is’itarabumbwa,Uhereye Kera Kose,Ur’uko Wahoze."
      ]
    },
    {
      "type": "verse",
      "number": 5,
      "lines": [
        "Imyaka Igihumbi Mana.Ni Myinshi Kuri Twe.",
        "Kuri  Wow’iguhwaniye N’umuns’umwe Gusa."
      ]
    },
    {
      "type": "verse",
      "number": 6,
      "lines": [
        "Imyaka Ijyan’iby’iyi  Si Nk’amaz’ahurura,",
        "Bikibagirana Vuba Nk’inzozi Z’umuntu."
      ]
    },
    {
      "type": "verse",
      "number": 7,
      "lines": [
        "Mana, Wadutabaraga Mu minsi yakera",
        "na non’uzaturengera tugeze kugupfa"
      ]
    }
  ]
}